rahrah/__init__.py
rahrah/cmap/__init__.py
rahrah/cmap/cmap.py
rahrah/palette/__init__.py
rahrah/palette/palette.py
rahrah-0.6.1.dist-info/METADATA
rahrah-0.6.1.dist-info/WHEEL
rahrah-0.6.1.dist-info/top_level.txt
rahrah-0.6.1.dist-info/RECORD
