Metadata-Version: 2.4
Name: rahrah
Version: 0.6.1
Summary: University-inspired Matplotlib palettes and colormaps.
Home-page: https://github.com/avapolzin/rahrah
Author: Ava Polzin
Author-email: apolzin@uchicago.edu
License: MIT
Classifier: Development Status :: 4 - Beta
Classifier: License :: OSI Approved :: MIT License
Classifier: Operating System :: OS Independent
Classifier: Programming Language :: Python
Requires-Python: >=3
Requires-Dist: matplotlib
Dynamic: author
Dynamic: author-email
Dynamic: classifier
Dynamic: description
Dynamic: description-content-type
Dynamic: home-page
Dynamic: license
Dynamic: requires-dist
Dynamic: requires-python
Dynamic: summary
